fcm_adapter/__init__.py
fcm_adapter/adapter.py
fcm_adapter-0.1.2.dist-info/LICENSE
fcm_adapter-0.1.2.dist-info/WHEEL
fcm_adapter-0.1.2.dist-info/METADATA
fcm_adapter-0.1.2.dist-info/RECORD
