Metadata-Version: 2.1
Name: fcm-adapter
Version: 0.1.2
Summary: Firebase Cloud Messaging Adapter
License: MIT
Requires-Python: >=3.8,<4.0
Classifier: License :: OSI Approved :: MIT License
Classifier: Programming Language :: Python :: 3
Classifier: Programming Language :: Python :: 3.8
Classifier: Programming Language :: Python :: 3.9
Classifier: Programming Language :: Python :: 3.10
Classifier: Programming Language :: Python :: 3.11
Requires-Dist: cryptography (>=43.0.0,<44.0.0)
Requires-Dist: httpx (>=0.23.3,<0.24.0)
Requires-Dist: pyjwt (>=2.8.0,<3.0.0)
